LICENSE
MANIFEST.in
README.rst
setup.py
AdafruitCharLCD/Adafruit_CharLCDPlate.py
AdafruitCharLCD/Adafruit_I2C.py
AdafruitCharLCD/Adafruit_MCP230xx.py
AdafruitCharLCD/__init__.py
Mopidy_16x2LCD.egg-info/PKG-INFO
Mopidy_16x2LCD.egg-info/SOURCES.txt
Mopidy_16x2LCD.egg-info/dependency_links.txt
Mopidy_16x2LCD.egg-info/entry_points.txt
Mopidy_16x2LCD.egg-info/not-zip-safe
Mopidy_16x2LCD.egg-info/requires.txt
Mopidy_16x2LCD.egg-info/top_level.txt
mopidy_16x2LCD/__init__.py
mopidy_16x2LCD/actor.py
mopidy_16x2LCD/ext.conf