Metadata-Version: 1.1
Name: Mopidy-16x2LCD
Version: 0.1.0
Summary: Mopidy frontend to see track name and volume on a 16x2 LCD
Home-page: https://github.com/spjoe/mopidy-16x2LCD
Author: Camillo Dell'mour
Author-email: cdellmour@gmail.com
License: Apache License, Version 2.0
Platform: UNKNOWN
Classifier: Intended Audience :: End Users/Desktop
Classifier: License :: OSI Approved :: Apache Software License
Classifier: Operating System :: OS Independent
Classifier: Programming Language :: Python :: 2
Classifier: Topic :: Multimedia :: Sound/Audio :: Players
